modules/alu.v
module alu(
    input [15:0] x, y,
    input zx, nx, zy, ny, f, no,
    output [15:0] out,
    output zr, ng
);
    wire [15:0] x1, y1, x2, y2, and_out, add_out, mux_out;

    assign x1 = zx ? 16'b0 : x;
    assign y1 = zy ? 16'b0 : y;
    assign x2 = nx ? ~x1 : x1;
    assign y2 = ny ? ~y1 : y1;
    assign and_out = x2 & y2;
    assign add_out = x2 + y2;
    assign mux_out = f ? add_out : and_out;
    assign out = no ? ~mux_out : mux_out;
    assign zr = (out == 16'b0);
    assign ng = out[15];
endmodule

// Testbench
module alu_tb;
    reg [15:0] x, y;
    reg zx, nx, zy, ny, f, no;
    wire [15:0] out;
    wire zr, ng;

    alu dut(
        .x(x), .y(y),
        .zx(zx), .nx(nx), .zy(zy), .ny(ny), .f(f), .no(no),
        .out(out), .zr(zr), .ng(ng)
    );

    initial begin
        $dumpfile("modules/alu.vcd");
        $dumpvars(0, alu_tb);

        // Test cases
        // Case 1: x + y
        x = 16'd10; y = 16'd5; zx = 0; nx = 0; zy = 0; ny = 0; f = 1; no = 0; #10;
        
        // Case 2: x - y
        x = 16'd10; y = 16'd5; zx = 0; nx = 1; zy = 0; ny = 0; f = 1; no = 1; #10;
        
        // Case 3: y - x
        x = 16'd5; y = 16'd10; zx = 0; nx = 0; zy = 0; ny = 1; f = 1; no = 1; #10;
        
        // Case 4: x & y
        x = 16'b1010101010101010; y = 16'b1100110011001100; zx = 0; nx = 0; zy = 0; ny = 0; f = 0; no = 0; #10;
        
        // Case 5: x | y
        x = 16'b1010101010101010; y = 16'b1100110011001100; zx = 0; nx = 1; zy = 0; ny = 1; f = 0; no = 1; #10;
        
        // Case 6: !x
        x = 16'b1010101010101010; y = 16'd0; zx = 0; nx = 1; zy = 1; ny = 0; f = 0; no = 0; #10;
        
        // Case 7: !y
        x = 16'd0; y = 16'b1010101010101010; zx = 1; nx = 0; zy = 0; ny = 1; f = 0; no = 0; #10;
        
        // Case 8: -x
        x = 16'd42; y = 16'd0; zx = 0; nx = 1; zy = 1; ny = 0; f = 1; no = 1; #10;
        
        // Case 9: -y
        x = 16'd0; y = 16'd42; zx = 1; nx = 0; zy = 0; ny = 1; f = 1; no = 1; #10;
        
        // Case 10: x + 1
        x = 16'd42; y = 16'd0; zx = 0; nx = 1; zy = 1; ny = 1; f = 1; no = 1; #10;

        $finish;
    end

    initial begin
        $monitor("Time=%0t x=%d y=%d zx=%b nx=%b zy=%b ny=%b f=%b no=%b out=%d zr=%b ng=%b", 
                 $time, x, y, zx, nx, zy, ny, f, no, out, zr, ng);
    end
endmodule

modules/alu.vcd
$date
	Tue Aug 06 03:40:21 2024
$end
$version
	Icarus Verilog
$end
$timescale
	1s
$end
$scope module alu_tb $end
$var wire 1 ! zr $end
$var wire 16 " out [15:0] $end
$var wire 1 # ng $end
$var reg 1 $ f $end
$var reg 1 % no $end
$var reg 1 & nx $end
$var reg 1 ' ny $end
$var reg 16 ( x [15:0] $end
$var reg 16 ) y [15:0] $end
$var reg 1 * zx $end
$var reg 1 + zy $end
$scope module dut $end
$var wire 16 , and_out [15:0] $end
$var wire 1 $ f $end
$var wire 1 % no $end
$var wire 1 & nx $end
$var wire 1 ' ny $end
$var wire 16 - x [15:0] $end
$var wire 16 . y [15:0] $end
$var wire 1 * zx $end
$var wire 1 + zy $end
$var wire 1 ! zr $end
$var wire 16 / y2 [15:0] $end
$var wire 16 0 y1 [15:0] $end
$var wire 16 1 x2 [15:0] $end
$var wire 16 2 x1 [15:0] $end
$var wire 16 3 out [15:0] $end
$var wire 1 # ng $end
$var wire 16 4 mux_out [15:0] $end
$var wire 16 5 add_out [15:0] $end
$upscope $end
$upscope $end
$enddefinitions $end
#0
$dumpvars
b1111 5
b1111 4
b1111 3
b1010 2
b1010 1
b101 0
b101 /
b101 .
b1010 -
b0 ,
0+
0*
b101 )
b1010 (
0'
0&
0%
1$
0#
b1111 "
0!
$end
#10
0#
b1111111111111010 4
b101 ,
b101 "
b101 3
b1111111111111010 5
b1111111111110101 1
1%
1&
#20
0!
b101 "
b101 3
b1111111111111010 4
b101 ,
b1111111111110101 /
b1111111111111010 5
b101 1
b1010 0
b101 2
1'
0&
b1010 )
b1010 .
b101 (
b101 -
#30
1#
b1000100010001000 "
b1000100010001000 3
b1000100010001000 ,
b1010101010101010 1
b1000100010001000 4
b111011101110110 5
b1100110011001100 /
b1100110011001100 0
b1010101010101010 2
0%
0$
0'
b1100110011001100 )
b1100110011001100 .
b1010101010101010 (
b1010101010101010 -
#40
b1000100010001 4
1#
b1000100010001 ,
b1110111011101110 "
b1110111011101110 3
b11001100110011 /
b1000100010001000 5
b101010101010101 1
1%
1'
1&
#50
1!
b0 4
0#
b0 ,
b0 "
b0 3
b101010101010101 5
b0 /
b0 0
0%
0'
1+
b0 )
b0 .
#60
b101010101010101 /
b1010101010101010 0
b101010101010101 5
b0 1
b0 2
1'
0+
0&
1*
b1010101010101010 )
b1010101010101010 .
b0 (
b0 -
#70
0#
0!
b101010 "
b101010 3
b1111111111010101 4
b0 /
b1111111111010101 5
b1111111111010101 1
b101010 2
b0 0
1%
1$
0'
1+
1&
0*
b0 )
b0 .
b101010 (
b101010 -
#80
0!
b101010 "
b101010 3
b1111111111010101 4
b1111111111010101 /
b101010 0
b1111111111010101 5
b0 1
b0 2
1'
0+
0&
1*
b101010 )
b101010 .
b0 (
b0 -
#90
b101011 "
b101011 3
b1111111111111111 /
b1111111111010100 4
b1111111111010101 ,
b1111111111010100 5
b1111111111010101 1
b101010 2
b0 0
1+
1&
0*
b0 )
b0 .
b101010 (
b101010 -
