modules/test.v
module myModule();
  reg clk;  // Declare a clock signal
  reg [3:0] counter;  // Declare a 4-bit counter

  initial begin
    $dumpfile("test.vcd");  // Create a VCD file named test.vcd
    $dumpvars(0, myModule);  // Dump all variables in the module

    clk = 0;
    counter = 0;
    
    repeat(16) begin
      #5 clk = ~clk;  // Toggle clock every 5 time units
      if (clk) counter = counter + 1;  // Increment counter on rising edge
    end

    $display("Simulation complete");
    $finish;
  end
endmodule

modules/test.vcd
$date
	Tue Aug 06 01:20:28 2024
$end
$version
	Icarus Verilog
$end
$timescale
	1s
$end
$scope module myModule $end
$var reg 1 ! clk $end
$var reg 4 " counter [3:0] $end
$upscope $end
$enddefinitions $end
#0
$dumpvars
b0 "
0!
$end
#5
b1 "
1!
#10
0!
#15
b10 "
1!
#20
0!
#25
b11 "
1!
#30
0!
#35
b100 "
1!
#40
0!
#45
b101 "
1!
#50
0!
#55
b110 "
1!
#60
0!
#65
b111 "
1!
#70
0!
#75
b1000 "
1!
